mentat/__init__.py
mentat/__main__.py
mentat/app.py
mentat/broadcast.py
mentat/change_conflict_resolution.py
mentat/code_change.py
mentat/code_change_display.py
mentat/code_context.py
mentat/code_edit_feedback.py
mentat/code_file.py
mentat/code_file_manager.py
mentat/code_map.py
mentat/commands.py
mentat/config_manager.py
mentat/conversation.py
mentat/default_config.json
mentat/diff_context.py
mentat/errors.py
mentat/git_handler.py
mentat/llm_api.py
mentat/logging_config.py
mentat/mentat_prompt_session.py
mentat/model_error.py
mentat/parsing.py
mentat/prompts.py
mentat/session.py
mentat/session_input.py
mentat/session_stream.py
mentat/streaming_printer.py
mentat/user_input_manager.py
mentat/utils.py
mentat/parsers/__init__.py
mentat/parsers/block_parser.py
mentat/parsers/change_display_helper.py
mentat/parsers/diff_utils.py
mentat/parsers/file_edit.py
mentat/parsers/parser.py
mentat/parsers/replacement_parser.py
mentat/parsers/split_diff_parser.py
mentat/parsers/unified_diff_parser.py
mentat/prompts/__init__.py
mentat/prompts/block_parser_prompt.txt
mentat/prompts/prompts.py
mentat/prompts/replacement_parser_prompt.txt
mentat/prompts/split_diff_parser_prompt.txt
mentat/prompts/unified_diff_parser_prompt.txt
mentat/terminal/__init__.py
mentat/terminal/client.py
mentat/terminal/output.py
mentat/terminal/prompt_completer.py
mentat/terminal/prompt_session.py
testbed/__init__.py
testbed/multifile_calculator/__init__.py
testbed/multifile_calculator/calculator.py
testbed/multifile_calculator/operations.py
tests/__init__.py
tests/benchmark_test.py
tests/broadcast_test.py
tests/code_change_test.py
tests/code_context_test.py
tests/code_file_manager_test.py
tests/codechange_test.py
tests/commands_test.py
tests/config_test.py
tests/conftest.py
tests/diff_context_test.py
tests/git_handler_test.py
tests/license_check.py
tests/measure_api_speed.py
tests/mentat_prompt_session_test.py
tests/model_error_test.py
tests/record_benchmark.py
tests/system_test.py
tests/ui_test.py
mentat_ai-0.1.16.dist-info/LICENSE
mentat_ai-0.1.16.dist-info/METADATA
mentat_ai-0.1.16.dist-info/WHEEL
mentat_ai-0.1.16.dist-info/entry_points.txt
mentat_ai-0.1.16.dist-info/top_level.txt
mentat_ai-0.1.16.dist-info/RECORD
