Metadata-Version: 2.1
Name: mentat-ai
Version: 0.1.16
Summary: AI coding assistant on your command line
License: Apache-2.0
Requires-Python: >=3.10
License-File: LICENSE
Requires-Dist: fire (==0.5.0)
Requires-Dist: openai (==0.27.8)
Requires-Dist: prompt-toolkit (==3.0.39)
Requires-Dist: Pygments (==2.15.1)
Requires-Dist: pytest (==7.4.0)
Requires-Dist: pytest-asyncio (==0.21.1)
Requires-Dist: pytest-mock (==3.11.1)
Requires-Dist: pytest-reportlog (==0.4.0)
Requires-Dist: python-dotenv (==1.0.0)
Requires-Dist: termcolor (==2.3.0)
Requires-Dist: tiktoken (==0.4.0)
Requires-Dist: typing-extensions (==4.7.1)
